{
  "columns": [
    "Rebounding",
    "Turnovers",
    "3Pt Volume",
    "Dawg 3P%",
    "Dawg Pace"
  ],
  "matchups": {
    "Duke_Siena": {
      "upset": 0.001,
      "index": 4.02,
      "factors": [
        "3.48",
        "4.24",
        "4.32",
        "0.90",
        "7.68"
      ]
    },
    "Ohio St._TCU": {
      "upset": 0.366,
      "index": 5.99,
      "factors": [
        "6.24",
        "6.48",
        "4.51",
        "3.62",
        "4.78"
      ]
    },
    "St. John's_Northern Iowa": {
      "upset": 0.136,
      "index": 5.51,
      "factors": [
        "2.44",
        "4.67",
        "3.51",
        "6.44",
        "8.48"
      ]
    },
    "Kansas_Cal Baptist": {
      "upset": 0.0724,
      "index": 5.26,
      "factors": [
        "7.54",
        "5.25",
        "2.00",
        "4.85",
        "6.58"
      ]
    },
    "Louisville_South Florida": {
      "upset": 0.2768,
      "index": 6.55,
      "factors": [
        "4.94",
        "6.35",
        "8.70",
        "3.95",
        "1.79"
      ]
    },
    "Michigan St._North Dakota St.": {
      "upset": 0.0351,
      "index": 6.38,
      "factors": [
        "4.25",
        "7.33",
        "5.05",
        "8.03",
        "6.05"
      ]
    },
    "UCLA_UCF": {
      "upset": 0.3191,
      "index": 5.79,
      "factors": [
        "6.65",
        "3.22",
        "2.55",
        "9.37",
        "4.65"
      ]
    },
    "Connecticut_Furman": {
      "upset": 0.0145,
      "index": 4.93,
      "factors": [
        "4.02",
        "2.62",
        "7.16",
        "4.25",
        "6.54"
      ]
    },
    "Arizona_LIU": {
      "upset": 0.001,
      "index": 3.83,
      "factors": [
        "3.36",
        "4.16",
        "0.18",
        "8.58",
        "4.40"
      ]
    },
    "Villanova_Utah St.": {
      "upset": 0.4933,
      "index": 6.94,
      "factors": [
        "4.91",
        "5.25",
        "7.32",
        "7.59",
        "4.36"
      ]
    },
    "Wisconsin_High Point": {
      "upset": 0.1334,
      "index": 6.76,
      "factors": [
        "5.08",
        "7.15",
        "8.37",
        "5.64",
        "2.46"
      ]
    },
    "Arkansas_Hawaii": {
      "upset": 0.0518,
      "index": 4.15,
      "factors": [
        "5.68",
        "3.26",
        "3.37",
        "1.81",
        "2.67"
      ]
    },
    "BYU_Texas": {
      "upset": 0.3789,
      "index": 6.01,
      "factors": [
        "5.64",
        "4.18",
        "4.37",
        "6.49",
        "5.68"
      ]
    },
    "BYU_N.C. State": {
      "upset": 0.3882,
      "index": 6.95,
      "factors": [
        "2.84",
        "6.39",
        "6.55",
        "9.70",
        "3.21"
      ]
    },
    "Gonzaga_Kennesaw St.": {
      "upset": 0.0166,
      "index": 4.08,
      "factors": [
        "4.36",
        "2.47",
        "3.78",
        "4.90",
        "2.57"
      ]
    },
    "Miami FL_Missouri": {
      "upset": 0.343,
      "index": 5.16,
      "factors": [
        "3.88",
        "3.70",
        "2.19",
        "6.52",
        "6.28"
      ]
    },
    "Purdue_Queens": {
      "upset": 0.0025,
      "index": 5.65,
      "factors": [
        "2.37",
        "4.35",
        "7.44",
        "8.19",
        "4.46"
      ]
    },
    "Florida_Prairie View A&M": {
      "upset": 0.001,
      "index": 3.16,
      "factors": [
        "0.88",
        "6.44",
        "2.30",
        "3.89",
        "1.94"
      ]
    },
    "Florida_Lehigh": {
      "upset": 0.001,
      "index": 4.34,
      "factors": [
        "0.68",
        "4.68",
        "4.14",
        "8.96",
        "5.43"
      ]
    },
    "Clemson_Iowa": {
      "upset": 0.4172,
      "index": 6.41,
      "factors": [
        "4.72",
        "4.38",
        "6.52",
        "5.37",
        "7.87"
      ]
    },
    "Vanderbilt_McNeese": {
      "upset": 0.1213,
      "index": 5.37,
      "factors": [
        "5.29",
        "5.62",
        "5.05",
        "1.34",
        "6.18"
      ]
    },
    "Nebraska_Troy": {
      "upset": 0.0538,
      "index": 6.09,
      "factors": [
        "6.75",
        "2.97",
        "9.05",
        "3.97",
        "7.45"
      ]
    },
    "North Carolina_VCU": {
      "upset": 0.3882,
      "index": 7.1,
      "factors": [
        "5.28",
        "5.86",
        "7.11",
        "8.77",
        "3.34"
      ]
    },
    "Illinois_Penn": {
      "upset": 0.0064,
      "index": 6.12,
      "factors": [
        "2.61",
        "6.13",
        "6.15",
        "9.73",
        "4.25"
      ]
    },
    "Saint Mary's_Texas A&M": {
      "upset": 0.3719,
      "index": 6.96,
      "factors": [
        "3.04",
        "7.19",
        "6.01",
        "8.96",
        "4.37"
      ]
    },
    "Houston_Idaho": {
      "upset": 0.0039,
      "index": 5.43,
      "factors": [
        "3.79",
        "2.80",
        "7.64",
        "5.97",
        "4.87"
      ]
    },
    "Michigan_UMBC": {
      "upset": 0.001,
      "index": 5.56,
      "factors": [
        "2.19",
        "5.83",
        "5.56",
        "8.19",
        "6.14"
      ]
    },
    "Michigan_Howard": {
      "upset": 0.001,
      "index": 4.77,
      "factors": [
        "4.28",
        "5.47",
        "4.29",
        "6.25",
        "3.21"
      ]
    },
    "Georgia_Saint Louis": {
      "upset": 0.4301,
      "index": 6.75,
      "factors": [
        "5.40",
        "2.87",
        "7.63",
        "9.97",
        "1.94"
      ]
    },
    "Texas Tech_Akron": {
      "upset": 0.1915,
      "index": 7.72,
      "factors": [
        "5.14",
        "6.71",
        "8.84",
        "9.78",
        "3.83"
      ]
    },
    "Alabama_Hofstra": {
      "upset": 0.1055,
      "index": 7.36,
      "factors": [
        "6.06",
        "4.56",
        "8.52",
        "9.15",
        "7.64"
      ]
    },
    "Tennessee_N.C. State": {
      "upset": 0.3191,
      "index": 6.53,
      "factors": [
        "2.02",
        "7.28",
        "4.30",
        "9.70",
        "4.35"
      ]
    },
    "Tennessee_Texas": {
      "upset": 0.2912,
      "index": 5.5,
      "factors": [
        "4.82",
        "5.07",
        "2.12",
        "6.49",
        "5.68"
      ]
    },
    "Virginia_Wright St.": {
      "upset": 0.0293,
      "index": 5.97,
      "factors": [
        "4.11",
        "5.20",
        "5.40",
        "8.60",
        "5.20"
      ]
    },
    "Kentucky_Santa Clara": {
      "upset": 0.4301,
      "index": 6.64,
      "factors": [
        "4.84",
        "6.34",
        "6.58",
        "6.38",
        "3.05"
      ]
    },
    "Iowa St._Tennessee St.": {
      "upset": 0.0012,
      "index": 4.06,
      "factors": [
        "4.57",
        "4.14",
        "2.58",
        "4.77",
        "3.58"
      ]
    }
  },
  "regions": {
    "East": [
      "Duke_Siena",
      "Ohio St._TCU",
      "St. John's_Northern Iowa",
      "Kansas_Cal Baptist",
      "Louisville_South Florida",
      "Michigan St._North Dakota St.",
      "UCLA_UCF",
      "Connecticut_Furman"
    ],
    "West": [
      "Arizona_LIU",
      "Villanova_Utah St.",
      "Wisconsin_High Point",
      "Arkansas_Hawaii",
      "BYU_Texas",
      "BYU_N.C. State",
      "Gonzaga_Kennesaw St.",
      "Miami FL_Missouri",
      "Purdue_Queens"
    ],
    "South": [
      "Florida_Prairie View A&M",
      "Florida_Lehigh",
      "Clemson_Iowa",
      "Vanderbilt_McNeese",
      "Nebraska_Troy",
      "North Carolina_VCU",
      "Illinois_Penn",
      "Saint Mary's_Texas A&M",
      "Houston_Idaho"
    ],
    "Midwest": [
      "Michigan_UMBC",
      "Michigan_Howard",
      "Georgia_Saint Louis",
      "Texas Tech_Akron",
      "Alabama_Hofstra",
      "Tennessee_N.C. State",
      "Tennessee_Texas",
      "Virginia_Wright St.",
      "Kentucky_Santa Clara",
      "Iowa St._Tennessee St."
    ]
  },
  "locations": {
    "East": [
      "Greenville, SC",
      "Greenville, SC",
      "San Diego, CA",
      "San Diego, CA",
      "Buffalo, NY",
      "Buffalo, NY",
      "Philadelphia, PA",
      "Philadelphia, PA"
    ],
    "West": [
      "San Diego, CA",
      "San Diego, CA",
      "Portland, OR",
      "Portland, OR",
      "Portland, OR",
      "Portland, OR",
      "Portland, OR",
      "St. Louis, MO",
      "St. Louis, MO"
    ],
    "South": [
      "Tampa, FL",
      "Tampa, FL",
      "Tampa, FL",
      "Oklahoma City, OK",
      "Oklahoma City, OK",
      "Greenville, SC",
      "Greenville, SC",
      "Oklahoma City, OK",
      "Oklahoma City, OK"
    ],
    "Midwest": [
      "Buffalo, NY",
      "Buffalo, NY",
      "Buffalo, NY",
      "Tampa, FL",
      "Tampa, FL",
      "Philadelphia, PA",
      "Philadelphia, PA",
      "Philadelphia, PA",
      "St. Louis, MO",
      "St. Louis, MO"
    ]
  }
}